LICENSE.txt
MANIFEST.in
README.md
setup.py
examples/cartesian_pose_robot.py
examples/cartesian_velocity_robot.py
examples/joint_position_robot.py
examples/joint_speed_robot.py
micropsi_integration_sdk/__init__.py
micropsi_integration_sdk/dev_client.py
micropsi_integration_sdk/dev_schema.py
micropsi_integration_sdk/dev_server.py
micropsi_integration_sdk/robot_interface_collection.py
micropsi_integration_sdk/robot_sdk.py
micropsi_integration_sdk/sandbox.py
micropsi_integration_sdk/toolbox.py
micropsi_integration_sdk/version.py
micropsi_integration_sdk.egg-info/PKG-INFO
micropsi_integration_sdk.egg-info/SOURCES.txt
micropsi_integration_sdk.egg-info/dependency_links.txt
micropsi_integration_sdk.egg-info/entry_points.txt
micropsi_integration_sdk.egg-info/requires.txt
micropsi_integration_sdk.egg-info/top_level.txt
tests/test_example_robots.py