Metadata-Version: 2.1
Name: micropsi-integration-sdk
Version: 0.24.0
Summary: Integration SDK for Micropsi Industries
Home-page: https://github.com/micropsi-industries/micropsi-integration-sdk
Author: Micropsi Industries
Author-email: contact@micropsi-industries.com
License: MIT
Platform: macosx-14-arm64
Requires-Python: >=3.6, <4
License-File: LICENSE.txt
Requires-Dist: numpy
Requires-Dist: pyquaternion
Provides-Extra: test
Requires-Dist: pytest; extra == "test"
